tkinterweb_tkhtml_extras/__init__.py
tkinterweb_tkhtml_extras/tkhtml/COPYRIGHT
tkinterweb_tkhtml_extras/tkhtml/manylinux1_x86_64/libTkhtml3.1.so
tkinterweb_tkhtml_extras/tkhtml/win_amd64/COPYING-CAIRO-LGPL-2.1
tkinterweb_tkhtml_extras/tkhtml/win_amd64/libTkhtml3.1.dll
tkinterweb_tkhtml_extras/tkhtml/win_amd64/libcairo-2.dll
tkinterweb_tkhtml_extras-1.2.0.dist-info/LICENSE.md
tkinterweb_tkhtml_extras-1.2.0.dist-info/METADATA
tkinterweb_tkhtml_extras-1.2.0.dist-info/WHEEL
tkinterweb_tkhtml_extras-1.2.0.dist-info/top_level.txt
tkinterweb_tkhtml_extras-1.2.0.dist-info/RECORD
